dv_flow/libcc/__ext__.py
dv_flow/libcc/__init__.py
dv_flow/libcc/exe.py
dv_flow/libcc/flow.dv
dv_flow/libcc/shared_lib.py
dv_flow_libcc-0.0.116977668219rc0.dist-info/licenses/LICENSE
dv_flow_libcc-0.0.116977668219rc0.dist-info/METADATA
dv_flow_libcc-0.0.116977668219rc0.dist-info/WHEEL
dv_flow_libcc-0.0.116977668219rc0.dist-info/entry_points.txt
dv_flow_libcc-0.0.116977668219rc0.dist-info/top_level.txt
dv_flow_libcc-0.0.116977668219rc0.dist-info/RECORD
