Metadata-Version: 2.4
Name: dv-flow-libcc
Version: 0.0.116977668219rc0
Summary: Tasks for building artifacts from C/C++ code
Author-email: Matthew Ballance <matt.ballance@gmail.com>
License:                                  Apache License
License-File: LICENSE
Requires-Dist: dv-flow-mgr
Dynamic: license-file
